{
  "tables": [
    "order_items",
    "products"
  ],
  "joins": [
    {
      "left_table": "t1 (order_items)",
      "right_table": "t2 (products)",
      "condition": "t1.product_id = t2.product_id"
    }
  ],
  "filters": [],
  "aggregations": [],
  "group_by": [
    "t1.product_id"
  ],
  "having": [],
  "select_columns": [
    "t2.product_details"
  ],
  "set_operations": [],
  "has_distinct": false,
  "has_subquery": false,
  "has_window_fn": false,
  "grain": "t1.product_id",
  "model_type": "fact"
}