{
  "tables": [
    "claims_processing",
    "claims_processing_stages"
  ],
  "joins": [
    {
      "left_table": "claims_processing",
      "right_table": "claims_processing_stages",
      "condition": "t1.claim_stage_id = t2.claim_stage_id"
    }
  ],
  "filters": [],
  "aggregations": [
    {
      "function": "COUNT",
      "column": "*",
      "alias": ""
    }
  ],
  "group_by": [
    "t1.claim_stage_id"
  ],
  "having": [],
  "select_columns": [
    "t2.claim_status_name"
  ],
  "set_operations": [],
  "has_distinct": false,
  "has_subquery": false,
  "has_window_fn": false,
  "grain": "t1.claim_stage_id",
  "model_type": "report"
}