{
  "tables": [
    "film",
    "inventory"
  ],
  "joins": [
    {
      "left_table": "T1",
      "right_table": "T2",
      "condition": "T1.film_id = T2.film_id"
    }
  ],
  "filters": [],
  "aggregations": [
    {
      "function": "COUNT",
      "column": "*",
      "alias": ""
    }
  ],
  "group_by": [
    "T1.film_id"
  ],
  "having": [],
  "select_columns": [
    "T1.title",
    "T1.film_id"
  ],
  "set_operations": [],
  "has_distinct": false,
  "has_subquery": false,
  "has_window_fn": false,
  "grain": "T1.film_id",
  "model_type": "report"
}