{
  "tables": [
    "airlines",
    "routes"
  ],
  "joins": [
    {
      "left_table": "airlines",
      "right_table": "routes",
      "condition": "T1.alid = T2.alid"
    }
  ],
  "filters": [
    "T1.name = 'American Airlines'"
  ],
  "aggregations": [
    {
      "function": "COUNT",
      "column": "*",
      "alias": ""
    }
  ],
  "group_by": [],
  "having": [],
  "select_columns": [
    "COUNT(*)"
  ],
  "set_operations": [],
  "has_distinct": false,
  "has_subquery": false,
  "has_window_fn": false,
  "grain": "",
  "model_type": "report"
}