{
  "tables": [
    "Ref_template_types",
    "Templates",
    "Documents"
  ],
  "joins": [
    {
      "left_table": "Ref_template_types",
      "right_table": "Templates",
      "condition": "T1.template_type_code = T2.template_type_code"
    },
    {
      "left_table": "Templates",
      "right_table": "Documents",
      "condition": "T2.Template_ID = T3.template_ID"
    }
  ],
  "filters": [],
  "aggregations": [],
  "group_by": [],
  "having": [],
  "select_columns": [
    "T1.template_type_description"
  ],
  "set_operations": [],
  "has_distinct": true,
  "has_subquery": false,
  "has_window_fn": false,
  "grain": "template_type_description",
  "model_type": "dimension"
}