{
  "tables": [
    "Tourist_Attractions",
    "VISITS"
  ],
  "joins": [
    {
      "left_table": "Tourist_Attractions",
      "right_table": "VISITS",
      "condition": "T1.Tourist_Attraction_ID = T2.Tourist_Attraction_ID"
    }
  ],
  "filters": [],
  "aggregations": [
    {
      "function": "COUNT",
      "column": "*",
      "alias": ""
    }
  ],
  "group_by": [
    "T2.Tourist_Attraction_ID"
  ],
  "having": [
    "COUNT(*) <= 1"
  ],
  "select_columns": [
    "T1.Name",
    "T1.Tourist_Attraction_ID"
  ],
  "set_operations": [],
  "has_distinct": false,
  "has_subquery": false,
  "has_window_fn": false,
  "grain": "T2.Tourist_Attraction_ID",
  "model_type": "report"
}